README.md
setup.py
YDbf.egg-info/PKG-INFO
YDbf.egg-info/SOURCES.txt
YDbf.egg-info/dependency_links.txt
YDbf.egg-info/entry_points.txt
YDbf.egg-info/top_level.txt
YDbf.egg-info/zip-safe
ydbf/__init__.py
ydbf/dump.py
ydbf/lib.py
ydbf/reader.py
ydbf/six.py
ydbf/test.py
ydbf/writer.py